[
  {
    "events": [],
    "venue": "Cat's Cradle",
    "success": false,
    "error": "No events found on the page",
    "scrapedAt": "2025-03-15T13:32:38.374Z"
  },
  {
    "events": [
      {
        "id": "07806dfb-6ec3-4882-8fae-e250d4abaac1",
        "name": "Manifest 7",
        "date": "2026-03-14T04:00:00.000Z",
        "type": "music",
        "description": "Manifest Music Festival Presents presents at Local 506",
        "startTime": "7pm",
        "venueId": "2",
        "sourceUrl": "https://www.etix.com/ticket/p/71473145/manifest-7-chapel-hill-local-506?partner_id=100",
        "lastScraped": "2025-03-15T13:32:40.602Z",
        "hash": "923d2728fe75025a01ce478d8317771b",
        "performers": [
          "Manifest 7"
        ]
      },
      {
        "id": "76d14204-41f3-45d1-8460-334b286db383",
        "name": "The Spectacles, The Unsustainables, and Hex Files",
        "date": "2025-03-16T04:00:00.000Z",
        "type": "music",
        "description": "Local 506 Presents presents at Local 506",
        "startTime": "7pm",
        "venueId": "2",
        "sourceUrl": "",
        "lastScraped": "2025-03-15T13:32:40.604Z",
        "hash": "cb7b81787fa48422897297eda1cad291",
        "performers": [
          "The Spectacles, The Unsustainables, and Hex Files"
        ]
      },
      {
        "id": "1085e3ab-21fa-40e7-a732-c029c267868b",
        "name": "Ashes to Amber with Current Blue",
        "date": "2025-03-19T04:00:00.000Z",
        "type": "music",
        "description": "Andmoreagain Presents presents at Local 506",
        "startTime": "",
        "venueId": "2",
        "sourceUrl": "https://tickets.venuepilot.com/e/127387",
        "lastScraped": "2025-03-15T13:32:40.605Z",
        "hash": "56c5542f7facae6b4f8958801f837672",
        "performers": [
          "Ashes to Amber with Current Blue"
        ]
      },
      {
        "id": "0904d813-55ea-4064-a5d1-f26413aba1ae",
        "name": "Superintendo with Oort Patrol and Ruler!",
        "date": "2025-03-20T04:00:00.000Z",
        "type": "music",
        "description": "Local 506 Presents presents at Local 506",
        "startTime": "7pm",
        "venueId": "2",
        "sourceUrl": "https://www.etix.com/ticket/p/89894102/superintendo-with-oort-patrol-and-ruler-chapel-hill-local-506?partner_id=100",
        "lastScraped": "2025-03-15T13:32:40.605Z",
        "hash": "d67745884f4a482d8ef39196a58aa100",
        "performers": [
          "Superintendo with Oort Patrol and Ruler!"
        ]
      },
      {
        "id": "95d44c92-2e31-4dd3-98f7-825f8984c4ef",
        "name": "Ray Bull",
        "date": "2025-03-21T04:00:00.000Z",
        "type": "music",
        "description": "Cat's Cradle Presents presents at Local 506",
        "startTime": "7pm",
        "venueId": "2",
        "sourceUrl": "https://catscradle.com/event/ray-bull/local-506/chapel-hill-north-carolina/",
        "lastScraped": "2025-03-15T13:32:40.606Z",
        "hash": "7211131cfa6d7b1b6faf24af0e8dcc89",
        "performers": [
          "Ray Bull"
        ]
      },
      {
        "id": "465cb3c5-f145-419f-ab45-09b2f6eede9e",
        "name": "Whores with Facet and Scrape",
        "date": "2025-03-22T04:00:00.000Z",
        "type": "music",
        "description": "Local 506 Presents presents at Local 506",
        "startTime": "7:30pm",
        "venueId": "2",
        "sourceUrl": "https://www.etix.com/ticket/p/95527161/whores-with-facet-and-scrape-chapel-hill-local-506?partner_id=100",
        "lastScraped": "2025-03-15T13:32:40.606Z",
        "hash": "835dd056caebcce6db984416d99e41d5",
        "performers": [
          "Whores with Facet and Scrape"
        ]
      },
      {
        "id": "5d46a759-dfe8-4340-8099-bdea1f8be378",
        "name": "Lawn Enforcement with Negative Feedback and Mush, Puppy!",
        "date": "2025-03-23T04:00:00.000Z",
        "type": "music",
        "description": "Local 506 Presents presents at Local 506",
        "startTime": "7pm",
        "venueId": "2",
        "sourceUrl": "https://www.etix.com/ticket/p/37706196/lawn-enforcement-with-negative-feedback-and-mushpuppy-chapel-hill-local-506?partner_id=100",
        "lastScraped": "2025-03-15T13:32:40.607Z",
        "hash": "a00676227290a4620f4e4029c351ca6c",
        "performers": [
          "Lawn Enforcement with Negative Feedback and Mush, Puppy!"
        ]
      },
      {
        "id": "9f10de46-1751-4fa9-a0db-da8046d4a4e1",
        "name": "Heart to Gold with Rosary, Weymouth, and Buck Swope",
        "date": "2025-03-24T04:00:00.000Z",
        "type": "music",
        "description": "Andmoreagain Presents presents at Local 506",
        "startTime": "7pm",
        "venueId": "2",
        "sourceUrl": "https://www.venuepilot.co/events/122981/orders/new",
        "lastScraped": "2025-03-15T13:32:40.608Z",
        "hash": "7a5c0958d49798ccb1079410d7395d9e",
        "performers": [
          "Heart to Gold with Rosary, Weymouth, and Buck Swope"
        ]
      },
      {
        "id": "1e29bc73-bbe0-445e-8dfc-71d5b56065e1",
        "name": "Cancerslug with Good Good Grief and Cigarettesmokingman",
        "date": "2025-03-27T04:00:00.000Z",
        "type": "music",
        "description": "Local 506 Presents presents at Local 506",
        "startTime": "7pm",
        "venueId": "2",
        "sourceUrl": "https://www.etix.com/ticket/p/34435285/cancerslug-with-good-good-grief-and-cigarettesmokingman-chapel-hill-local-506?partner_id=100",
        "lastScraped": "2025-03-15T13:32:40.609Z",
        "hash": "3b19afe31cfd36719b5b6da0b6dd498f",
        "performers": [
          "Cancerslug with Good Good Grief and Cigarettesmokingman"
        ]
      },
      {
        "id": "aa3fbe67-23ed-4879-96a6-4433d42a4030",
        "name": "Dogwood Tales with Owen FitzGerald and Brian McGee",
        "date": "2025-03-28T04:00:00.000Z",
        "type": "music",
        "description": "Local 506 Presents presents at Local 506",
        "startTime": "7pm",
        "venueId": "2",
        "sourceUrl": "https://www.etix.com/ticket/p/44665939/dogwood-tales-with-owen-fitzgerald-and-brian-mcgee-chapel-hill-local-506?partner_id=100",
        "lastScraped": "2025-03-15T13:32:40.610Z",
        "hash": "815fdade9314f89c87b856b126ee6ac2",
        "performers": [
          "Dogwood Tales with Owen FitzGerald and Brian McGee"
        ]
      },
      {
        "id": "39d992f5-78b6-433f-888a-469a37d8eb53",
        "name": "The Bleu Ball: Jean-Belle’s Punk Rock B-Day Bash",
        "date": "2025-03-29T04:00:00.000Z",
        "type": "music",
        "description": "Local 506 Presents presents at Local 506",
        "startTime": "9:30pm",
        "venueId": "2",
        "sourceUrl": "https://www.etix.com/ticket/p/82524734/the-bleu-balljeanbelles-punk-rock-bday-bash-chapel-hill-local-506?partner_id=100",
        "lastScraped": "2025-03-15T13:32:40.610Z",
        "hash": "055c83ff9fa42e3eb461e1a8c92022ef",
        "performers": [
          "The Bleu Ball: Jean-Belle’s Punk Rock B-Day Bash"
        ]
      },
      {
        "id": "21c917b5-19ec-4010-ae4a-c956a78bf9d2",
        "name": "Cloakroom with Napalm Cruiser and Applefield",
        "date": "2025-03-30T04:00:00.000Z",
        "type": "music",
        "description": "Andmoreagain Presents presents at Local 506",
        "startTime": "7pm",
        "venueId": "2",
        "sourceUrl": "https://tickets.venuepilot.com/e/130440",
        "lastScraped": "2025-03-15T13:32:40.611Z",
        "hash": "6d6bc456452e6df592b62aa4302e0fc6",
        "performers": [
          "Cloakroom with Napalm Cruiser and Applefield"
        ]
      },
      {
        "id": "6bb5866c-ddd6-4455-9d50-64bbda724969",
        "name": "Temptress and Thunderchief with The Magpie",
        "date": "2025-04-03T04:00:00.000Z",
        "type": "music",
        "description": "Local 506 Presents presents at Local 506",
        "startTime": "7pm",
        "venueId": "2",
        "sourceUrl": "https://www.etix.com/ticket/p/38011903/temptress-and-thunderchief-with-the-magpie-chapel-hill-local-506?partner_id=100",
        "lastScraped": "2025-03-15T13:32:40.611Z",
        "hash": "f2dc56759e06313973eea417304c99a2",
        "performers": [
          "Temptress and Thunderchief with The Magpie"
        ]
      },
      {
        "id": "3f6b7dc7-1b41-41cb-b5ea-712d27bc9e37",
        "name": "senses with Negative 25, Mvssie",
        "date": "2025-04-04T04:00:00.000Z",
        "type": "music",
        "description": "Andmoreagain Presents presents at Local 506",
        "startTime": "6:30pm",
        "venueId": "2",
        "sourceUrl": "https://tickets.venuepilot.com/e/125268",
        "lastScraped": "2025-03-15T13:32:40.612Z",
        "hash": "05191c873135c0a318ec749a570f5324",
        "performers": [
          "senses with Negative 25, Mvssie"
        ]
      },
      {
        "id": "73c1ce9e-f0a3-48bf-a276-5862833aa378",
        "name": "Manic Third Planet EP Release Show with Narsick",
        "date": "2025-04-05T04:00:00.000Z",
        "type": "music",
        "description": "Local 506 Presents presents at Local 506",
        "startTime": "7pm",
        "venueId": "2",
        "sourceUrl": "https://www.etix.com/ticket/p/61286863/manic-third-planet-ep-release-show-with-narsick-chapel-hill-local-506?partner_id=100",
        "lastScraped": "2025-03-15T13:32:40.612Z",
        "hash": "88bc1586d3334d05bb3587a5488c8538",
        "performers": [
          "Manic Third Planet EP Release Show with Narsick"
        ]
      },
      {
        "id": "3ed7d74a-da88-464b-b83c-d816c18229b2",
        "name": "Transviolet with Annabel Lee, Mixie",
        "date": "2025-04-06T04:00:00.000Z",
        "type": "music",
        "description": "Cat's Cradle Presents presents at Local 506",
        "startTime": "7pm",
        "venueId": "2",
        "sourceUrl": "826628.1646705385.1739988861-185969892.1717019010&_gl=1*1qlafni*_ga*MTg1OTY5ODkyLjE3MTcwMTkwMTA.*_ga_QDDJ0LYGZE*MTczOTk4ODg2MS4zNi4xLjE3Mzk5ODg4NzQuMC4wLjA.",
        "lastScraped": "2025-03-15T13:32:40.613Z",
        "hash": "8d2fb2f4f39976dad94e961375b9d6d5",
        "performers": [
          "Transviolet with Annabel Lee, Mixie"
        ]
      },
      {
        "id": "1002ec09-0ae8-4c9e-bbfc-ef4354892aba",
        "name": "Slow Joy with Flycatcher and Goddamn Wolves",
        "date": "2025-04-08T04:00:00.000Z",
        "type": "music",
        "description": "Event at Local 506",
        "startTime": "6:30pm",
        "venueId": "2",
        "sourceUrl": "https://tickets.venuepilot.com/e/129245",
        "lastScraped": "2025-03-15T13:32:40.613Z",
        "hash": "d2c547050447f5761abaa515863caf52",
        "performers": [
          "Slow Joy with Flycatcher and Goddamn Wolves"
        ]
      },
      {
        "id": "baf61c78-465b-420d-9c8d-fff4f50695f1",
        "name": "New Translations – Vacation Tour 2025",
        "date": "2025-04-10T04:00:00.000Z",
        "type": "music",
        "description": "Crank It Loud presents at Local 506",
        "startTime": "6pm",
        "venueId": "2",
        "sourceUrl": "https://www.etix.com/ticket/p/62837641/new-translations-vacation-tour-2025-chapel-hill-local-506-cil?partner_id=100",
        "lastScraped": "2025-03-15T13:32:40.614Z",
        "hash": "7eb1d1768651399f9ddfd8270cca3c3c",
        "performers": [
          "New Translations – Vacation Tour 2025"
        ]
      },
      {
        "id": "4d382558-805c-41a4-b309-d17197669fb5",
        "name": "Excercise, Blous3, Quinine, Faeryring",
        "date": "2025-04-11T04:00:00.000Z",
        "type": "music",
        "description": "Local 506 Presents presents at Local 506",
        "startTime": "7pm",
        "venueId": "2",
        "sourceUrl": "https://www.etix.com/ticket/p/71305850/excerciseblous3quininefaeryring-chapel-hill-local-506?partner_id=100",
        "lastScraped": "2025-03-15T13:32:40.614Z",
        "hash": "61394aac996befb7a0bf0ebaba626fc8",
        "performers": [
          "Excercise, Blous3, Quinine, Faeryring"
        ]
      },
      {
        "id": "f00fb77a-1086-4394-b1dd-1666f0e62a2a",
        "name": "First To Eleven – ‘Full Steam Ahead’ Tour",
        "date": "2025-04-12T04:00:00.000Z",
        "type": "music",
        "description": "Crank It Loud presents at Local 506",
        "startTime": "7pm",
        "venueId": "2",
        "sourceUrl": "https://www.etix.com/ticket/p/58881414/first-to-eleven-full-steam-aheadtour-chapel-hill-local-506-cil?partner_id=100",
        "lastScraped": "2025-03-15T13:32:40.615Z",
        "hash": "1e1fdc45335d684ff3977c5282ae8e03",
        "performers": [
          "First To Eleven – ‘Full Steam Ahead’ Tour"
        ]
      },
      {
        "id": "2b2cacad-d2e9-4274-978c-f6fcf6f2b951",
        "name": "Pity Party (Girls Club) with Foxtide",
        "date": "2025-04-13T04:00:00.000Z",
        "type": "music",
        "description": "Local 506 Presents presents at Local 506",
        "startTime": "7pm",
        "venueId": "2",
        "sourceUrl": "https://www.etix.com/ticket/p/94311634/pity-party-girls-clubwith-foxtide-chapel-hill-local-506?partner_id=100",
        "lastScraped": "2025-03-15T13:32:40.616Z",
        "hash": "4f6ea74262d167bbe5567890ad658abc",
        "performers": [
          "Pity Party (Girls Club) with Foxtide"
        ]
      },
      {
        "id": "baf4603b-07ca-44b4-bfc6-2b998e1ceabd",
        "name": "Shayfer James with Sparkbird",
        "date": "2025-04-14T04:00:00.000Z",
        "type": "music",
        "description": "Andmoreagain Presents presents at Local 506",
        "startTime": "7pm",
        "venueId": "2",
        "sourceUrl": "https://tickets.venuepilot.com/e/124797",
        "lastScraped": "2025-03-15T13:32:40.616Z",
        "hash": "e1f5c017822fb41518d0b800007663b8",
        "performers": [
          "Shayfer James with Sparkbird"
        ]
      },
      {
        "id": "88bcd825-1cc9-48c8-83fe-34fd7c84a7a8",
        "name": "The Punk Rap Tour: Kool Keith and MC Homeless with DJ Halo, Marc Live, J Stylez, and Geeked",
        "date": "2025-04-15T04:00:00.000Z",
        "type": "music",
        "description": "Local 506 Presents presents at Local 506",
        "startTime": "7pm",
        "venueId": "2",
        "sourceUrl": "https://www.etix.com/ticket/p/61182003/the-punk-rap-tourkool-keith-and-mc-homeless-with-dj-halomarc-livej-stylezand-geeked-chapel-hill-local-506?partner_id=100",
        "lastScraped": "2025-03-15T13:32:40.617Z",
        "hash": "a536a337a33eda10a02990d69e012552",
        "performers": [
          "The Punk Rap Tour: Kool Keith and MC Homeless with DJ Halo, Marc Live, J Stylez, and Geeked"
        ]
      },
      {
        "id": "213abf78-1cac-4230-9054-38ed7106e7d3",
        "name": "The Ivy with Lyncs and Waking April",
        "date": "2025-04-17T04:00:00.000Z",
        "type": "music",
        "description": "Local 506 Presents presents at Local 506",
        "startTime": "7pm",
        "venueId": "2",
        "sourceUrl": "https://www.etix.com/ticket/p/31169689/the-ivy-with-lyncs-and-waking-april-chapel-hill-local-506?partner_id=100",
        "lastScraped": "2025-03-15T13:32:40.617Z",
        "hash": "4fb6d59f39427c5d982b2e74e8524fbe",
        "performers": [
          "The Ivy with Lyncs and Waking April"
        ]
      },
      {
        "id": "4afbcc4c-4edf-4494-bca0-e30c9fb15b86",
        "name": "Daisy The Great – Ballerina Tour with Benét",
        "date": "2025-04-18T04:00:00.000Z",
        "type": "music",
        "description": "Andmoreagain Presents presents at Local 506",
        "startTime": "",
        "venueId": "2",
        "sourceUrl": "https://www.venuepilot.co/events/122621/orders/new",
        "lastScraped": "2025-03-15T13:32:40.618Z",
        "hash": "c0eff88be4293e8fc56b2d540b0ef03c",
        "performers": [
          "Daisy The Great – Ballerina Tour with Benét"
        ]
      },
      {
        "id": "fad80494-0b67-49da-9c78-e1ebe0514652",
        "name": "Cold with September Mourning, University Drive, Thrower",
        "date": "2025-04-19T04:00:00.000Z",
        "type": "music",
        "description": "Andmoreagain Presents presents at Local 506",
        "startTime": "6pm",
        "venueId": "2",
        "sourceUrl": "https://tickets.venuepilot.com/e/127075",
        "lastScraped": "2025-03-15T13:32:40.618Z",
        "hash": "76f0a139d17e170f68f68455ccde24e6",
        "performers": [
          "Cold with September Mourning, University Drive, Thrower"
        ]
      },
      {
        "id": "0cf4291c-ce1c-449e-bb20-f6a578924f12",
        "name": "Youth Lagoon: Rarely Do I Dream Tour with Valley James",
        "date": "2025-04-20T04:00:00.000Z",
        "type": "music",
        "description": "Andmoreagain Presents presents at Local 506",
        "startTime": "7pm",
        "venueId": "2",
        "sourceUrl": "https://tickets.venuepilot.com/e/125386",
        "lastScraped": "2025-03-15T13:32:40.618Z",
        "hash": "c19b390ad5b090868956b70b01c88cf7",
        "performers": [
          "Youth Lagoon: Rarely Do I Dream Tour with Valley James"
        ]
      },
      {
        "id": "87da35d9-40fb-4df1-9eab-0083d27ae4fc",
        "name": "General Purpose with Sweet Dream and Monadi",
        "date": "2025-04-22T04:00:00.000Z",
        "type": "music",
        "description": "Local 506 Presents presents at Local 506",
        "startTime": "7pm",
        "venueId": "2",
        "sourceUrl": "https://www.etix.com/ticket/p/74587606/general-purpose-with-sweet-dream-and-monadi-chapel-hill-local-506?partner_id=100",
        "lastScraped": "2025-03-15T13:32:40.619Z",
        "hash": "54388b4634a97e9b3c8cb6cc5caea419",
        "performers": [
          "General Purpose with Sweet Dream and Monadi"
        ]
      },
      {
        "id": "c67db9d6-92c9-417f-a3b0-893b846fc017",
        "name": "Oceanic with Pageant",
        "date": "2025-04-25T04:00:00.000Z",
        "type": "music",
        "description": "Local 506 Presents presents at Local 506",
        "startTime": "7pm",
        "venueId": "2",
        "sourceUrl": "https://www.etix.com/ticket/p/81268770/oceanic-with-pageant-chapel-hill-local-506?partner_id=100",
        "lastScraped": "2025-03-15T13:32:40.619Z",
        "hash": "ce192bba905c0fa8b37901edb3bd0654",
        "performers": [
          "Oceanic with Pageant"
        ]
      },
      {
        "id": "db6f268d-95be-4bfc-8073-162d2b3257bd",
        "name": "R.A.P. Ferreira with BLAX",
        "date": "2025-04-28T04:00:00.000Z",
        "type": "music",
        "description": "Local 506 Presents presents at Local 506",
        "startTime": "7pm",
        "venueId": "2",
        "sourceUrl": "https://www.etix.com/ticket/p/65352846/rapferreira-with-blax-chapel-hill-local-506?partner_id=100",
        "lastScraped": "2025-03-15T13:32:40.619Z",
        "hash": "330a5e90938ccca1d2b5732346a7e670",
        "performers": [
          "R.A.P. Ferreira with BLAX"
        ]
      },
      {
        "id": "0717d25c-4799-4566-b13d-caaf3a6c20db",
        "name": "After Midnight Chappell Roan Dance Party: A Night of Bubblegum Pop Disco",
        "date": "2025-05-03T04:00:00.000Z",
        "type": "music",
        "description": "GBH Events X Local 506 Presents presents at Local 506",
        "startTime": "8pm",
        "venueId": "2",
        "sourceUrl": "https://www.etix.com/ticket/p/99371093/after-midnight-chappell-roan-dance-partya-night-of-bubblegum-pop-disco-chapel-hill-local-506?partner_id=100",
        "lastScraped": "2025-03-15T13:32:40.620Z",
        "hash": "3ef07fc796a4dc9e4164bc64f1b5adbf",
        "performers": [
          "After Midnight Chappell Roan Dance Party: A Night of Bubblegum Pop Disco"
        ]
      },
      {
        "id": "e26aeb96-4c5b-426a-bf0c-2def37dee79d",
        "name": "DeathByRomy with heffy",
        "date": "2025-05-04T04:00:00.000Z",
        "type": "music",
        "description": "Andmoreagain Presents presents at Local 506",
        "startTime": "7pm",
        "venueId": "2",
        "sourceUrl": "https://tickets.venuepilot.com/e/129190",
        "lastScraped": "2025-03-15T13:32:40.620Z",
        "hash": "5ea0c341bfdeb43ea1555e0d23bb8771",
        "performers": [
          "DeathByRomy with heffy"
        ]
      },
      {
        "id": "7a7bb900-d672-4d34-9216-c835b48126a3",
        "name": "Hackensaw Boys “Love What You Do” 20 Year Anniversary Tour",
        "date": "2025-05-09T04:00:00.000Z",
        "type": "music",
        "description": "Local 506 Presents presents at Local 506",
        "startTime": "7pm",
        "venueId": "2",
        "sourceUrl": "https://www.etix.com/ticket/p/98715195/hackensaw-boys-love-what-you-do20-year-anniversary-tour-chapel-hill-local-506?partner_id=100",
        "lastScraped": "2025-03-15T13:32:40.620Z",
        "hash": "2674d90936004b26617283821edb7018",
        "performers": [
          "Hackensaw Boys “Love What You Do” 20 Year Anniversary Tour"
        ]
      },
      {
        "id": "bdb14a33-907d-4e0b-8b13-473d4032eacc",
        "name": "SUICIDAL-IDOL and rouri404 with Vaeo",
        "date": "2025-05-10T04:00:00.000Z",
        "type": "music",
        "description": "Local 506 Presents presents at Local 506",
        "startTime": "7pm",
        "venueId": "2",
        "sourceUrl": "https://www.etix.com/ticket/p/86521553/suicidalidol-and-rouri404-with-vaeo-chapel-hill-local-506?partner_id=100",
        "lastScraped": "2025-03-15T13:32:40.621Z",
        "hash": "4782b37de8a1d9049cd3747ce9a1bef7",
        "performers": [
          "SUICIDAL-IDOL and rouri404 with Vaeo"
        ]
      },
      {
        "id": "b47877cc-feda-4756-9006-d368e4cc83bb",
        "name": "The Bones of J.R. Jones",
        "date": "2025-05-14T04:00:00.000Z",
        "type": "music",
        "description": "Andmoreagain Presents presents at Local 506",
        "startTime": "7pm",
        "venueId": "2",
        "sourceUrl": "https://tickets.venuepilot.com/e/130535",
        "lastScraped": "2025-03-15T13:32:40.621Z",
        "hash": "549a0afaa19b6962c90aba276cd87e5d",
        "performers": [
          "The Bones of J.R. Jones"
        ]
      },
      {
        "id": "a9c34d39-b03c-4d00-bab7-ae134bfc3949",
        "name": "TRSH with doan, Summerbruise, Dear Maryanne",
        "date": "2025-05-15T04:00:00.000Z",
        "type": "music",
        "description": "Andmoreagain Presents presents at Local 506",
        "startTime": "6:30pm",
        "venueId": "2",
        "sourceUrl": "https://tickets.venuepilot.com/e/130603",
        "lastScraped": "2025-03-15T13:32:40.622Z",
        "hash": "d05e693f759ca38cbb6fbc7374155672",
        "performers": [
          "TRSH with doan, Summerbruise, Dear Maryanne"
        ]
      },
      {
        "id": "94129075-a472-46d1-b959-50677849dc31",
        "name": "Pinko with Night! Night!, Treasure Pains, and Covenant Eye",
        "date": "2025-05-18T04:00:00.000Z",
        "type": "music",
        "description": "Local 506 Presents presents at Local 506",
        "startTime": "7pm",
        "venueId": "2",
        "sourceUrl": "https://www.etix.com/ticket/p/58451660/pinko-with-nightnighttreasure-painsand-covenant-eye-chapel-hill-local-506?partner_id=100",
        "lastScraped": "2025-03-15T13:32:40.622Z",
        "hash": "f064304f250ba7c6fea403bee7ecfb13",
        "performers": [
          "Pinko with Night! Night!, Treasure Pains, and Covenant Eye"
        ]
      },
      {
        "id": "7e4ed51d-5e31-43fe-827e-0fc129182cf8",
        "name": "Anubis The Dog Tour: Klokwork E with Gavyn Gun, The Hooliganz, Krackle Kapone, Crashout Artist, and Lo",
        "date": "2025-05-20T04:00:00.000Z",
        "type": "music",
        "description": "Local 506 Presents presents at Local 506",
        "startTime": "7pm",
        "venueId": "2",
        "sourceUrl": "https://www.etix.com/ticket/p/86031843/anubis-the-dog-tourklokwork-e-with-gavyn-gunthe-hooliganzkrackle-kaponecrashout-artistand-lo-chapel-hill-local-506?partner_id=100",
        "lastScraped": "2025-03-15T13:32:40.622Z",
        "hash": "6ced73bb85f00bd82addbb5db14ed154",
        "performers": [
          "Anubis The Dog Tour: Klokwork E with Gavyn Gun, The Hooliganz, Krackle Kapone, Crashout Artist, and Lo"
        ]
      },
      {
        "id": "39ffb5cf-a120-48d9-9d16-fef63560cd14",
        "name": "Young Medicine",
        "date": "2025-05-21T04:00:00.000Z",
        "type": "music",
        "description": "Cat's Cradle Presents presents at Local 506",
        "startTime": "7pm",
        "venueId": "2",
        "sourceUrl": "https://www.etix.com/ticket/p/58756566/young-medicine-chapel-hill-local-506-cats-cradle-presents?partner_id=100",
        "lastScraped": "2025-03-15T13:32:40.623Z",
        "hash": "f41f6702cd84993581f4baa66ad6e9be",
        "performers": [
          "Young Medicine"
        ]
      },
      {
        "id": "c57b72ec-ef05-4a8a-97e3-d9664edb932a",
        "name": "Slackjaw with Parris Bridge",
        "date": "2025-05-23T04:00:00.000Z",
        "type": "music",
        "description": "Andmoreagain Presents presents at Local 506",
        "startTime": "7pm",
        "venueId": "2",
        "sourceUrl": "https://tickets.venuepilot.com/e/slackjaw-2025-05-23-local-506-chapel-hill-a96d48",
        "lastScraped": "2025-03-15T13:32:40.623Z",
        "hash": "0a101b835f0a87f5f868eea2e2eaeb16",
        "performers": [
          "Slackjaw with Parris Bridge"
        ]
      },
      {
        "id": "14a29a79-e10a-40c6-9464-22871bd3dc72",
        "name": "Max Diaz",
        "date": "2025-05-24T04:00:00.000Z",
        "type": "music",
        "description": "Local 506 Presents presents at Local 506",
        "startTime": "7pm",
        "venueId": "2",
        "sourceUrl": "https://www.etix.com/ticket/p/34240419/max-diaz-chapel-hill-local-506?partner_id=100",
        "lastScraped": "2025-03-15T13:32:40.624Z",
        "hash": "105990e574fbe7f80308356884adeb71",
        "performers": [
          "Max Diaz"
        ]
      },
      {
        "id": "6427e81e-cdea-474d-b509-f54f224d3f21",
        "name": "Heathen Sun with Laniidae, Feverhill, and Mourning Lotus",
        "date": "2025-05-30T04:00:00.000Z",
        "type": "music",
        "description": "Sunflower and Madhattor Presents: presents at Local 506",
        "startTime": "7pm",
        "venueId": "2",
        "sourceUrl": "https://www.etix.com/ticket/p/85155604/heathen-sun-with-laniidaefeverhilland-mourning-lotus-chapel-hill-local-506?partner_id=100",
        "lastScraped": "2025-03-15T13:32:40.624Z",
        "hash": "63ce30ba33c9337872f5a99bfb1454d7",
        "performers": [
          "Heathen Sun with Laniidae, Feverhill, and Mourning Lotus"
        ]
      },
      {
        "id": "4f63e2ee-fbce-4f71-8199-ca59e3ee9799",
        "name": "The Pink Stones",
        "date": "2025-05-31T04:00:00.000Z",
        "type": "music",
        "description": "Local 506 Presents presents at Local 506",
        "startTime": "7pm",
        "venueId": "2",
        "sourceUrl": "https://www.etix.com/ticket/p/36779672/the-pink-stones-chapel-hill-local-506?partner_id=100",
        "lastScraped": "2025-03-15T13:32:40.625Z",
        "hash": "92783f67f88debdf77933738e3086c03",
        "performers": [
          "The Pink Stones"
        ]
      },
      {
        "id": "b29a21c4-c40b-4e66-a149-cee1b7e725df",
        "name": "Strictly 4 The Underground: Kev-O with Justen Best, Camz, Wuuudidit, Jon Lamar, Till OJ",
        "date": "2025-06-21T04:00:00.000Z",
        "type": "music",
        "description": "4th Room Entertainment Presents presents at Local 506",
        "startTime": "7pm",
        "venueId": "2",
        "sourceUrl": "https://www.etix.com/ticket/p/45771223/strictly-4-the-undergroundkevo-with-justen-bestcamzwuuudiditjon-lamartill-oj-chapel-hill-local-506?partner_id=100",
        "lastScraped": "2025-03-15T13:32:40.626Z",
        "hash": "a49363d21295b208ecd957a38ebcea4c",
        "performers": [
          "Strictly 4 The Underground: Kev-O with Justen Best, Camz, Wuuudidit, Jon Lamar, Till OJ"
        ]
      },
      {
        "id": "c4d711d5-54d8-4144-9ea5-a637605289c2",
        "name": "Bambara",
        "date": "2025-09-20T04:00:00.000Z",
        "type": "music",
        "description": "Andmoreagain Presents presents at Local 506",
        "startTime": "7pm",
        "venueId": "2",
        "sourceUrl": "https://tickets.venuepilot.com/e/bambara-2025-09-20-local-506-chapel-hill-198cba",
        "lastScraped": "2025-03-15T13:32:40.626Z",
        "hash": "d185d02b7332ee00983fc87cb7c2c94f",
        "performers": [
          "Bambara"
        ]
      }
    ],
    "venue": "Local 506",
    "success": true,
    "scrapedAt": "2025-03-15T13:32:40.626Z"
  },
  {
    "venue": "Motorco Music Hall",
    "events": [
      {
        "id": "7a151b98-c02c-4832-aff5-d82ebd478a54",
        "name": "Take On Me An 80s Affair 3 with THE 80'S DANSE SOCIETY / DJ FIFI HI-FI & PATRICK",
        "date": "2025-03-15T04:00:00.000Z",
        "type": "music",
        "description": "Event at Motorco Music Hall: Take On Me An 80s Affair 3 with THE 80'S DANSE SOCIETY / DJ FIFI HI-FI & PATRICK. Tickets $20/$23",
        "startTime": "8:00 pm",
        "venueId": "3",
        "sourceUrl": "https://motorcomusic.com/event/take-on-me-an-80s-affair-3/",
        "lastScraped": "2025-03-15T13:32:44.143Z",
        "hash": "addde060ba87a805107d188fc3e94abd",
        "performers": [
          "Take On Me An 80s Affair 3",
          "PATRICK"
        ]
      },
      {
        "id": "5444c62e-aa26-4c7a-8364-1cd6bcf686d0",
        "name": "Donovan Woods with BILLY RAFFOUL",
        "date": "2025-03-16T04:00:00.000Z",
        "type": "music",
        "description": "Event at Motorco Music Hall: Donovan Woods with BILLY RAFFOUL. Tickets $25/$27",
        "startTime": "8:00 pm",
        "venueId": "3",
        "sourceUrl": "https://motorcomusic.com/event/donovan-woods/",
        "lastScraped": "2025-03-15T13:32:44.143Z",
        "hash": "44a528b3593b9e6f0d2e4faf2d441390",
        "performers": [
          "Donovan Woods",
          "BILLY RAFFOUL"
        ]
      },
      {
        "id": "d73f3492-5caf-45c2-ad93-b9f82a894092",
        "name": "Willis with BRAVE BABY",
        "date": "2025-03-17T04:00:00.000Z",
        "type": "music",
        "description": "Event at Motorco Music Hall: Willis with BRAVE BABY. Tickets $18/$22",
        "startTime": "8:00 pm",
        "venueId": "3",
        "sourceUrl": "https://motorcomusic.com/event/willis/",
        "lastScraped": "2025-03-15T13:32:44.144Z",
        "hash": "01cd5152074afadd832ca9e8f6e08208",
        "performers": [
          "Willis",
          "BRAVE BABY"
        ]
      },
      {
        "id": "ffdbf167-a8c0-461b-8aba-cc8c9f194b92",
        "name": "The Monti Storyslam Lucky Break",
        "date": "2025-03-18T04:00:00.000Z",
        "type": "music",
        "description": "Event at Motorco Music Hall: The Monti Storyslam Lucky Break. Tickets $12",
        "startTime": "7:30 pm",
        "venueId": "3",
        "sourceUrl": "https://motorcomusic.com/event/the-monti-storyslam-lucky-break/",
        "lastScraped": "2025-03-15T13:32:44.144Z",
        "hash": "9ee8c580a793734d63217a4a3a00746c",
        "performers": [
          "The Monti Storyslam Lucky Break"
        ]
      },
      {
        "id": "206ab6a0-6338-477f-9f16-e3d25b52f93d",
        "name": "Reggie Watts",
        "date": "2025-03-19T04:00:00.000Z",
        "type": "music",
        "description": "Event at Motorco Music Hall: Reggie Watts. Tickets $39.50/$45",
        "startTime": "8:30 pm",
        "venueId": "3",
        "sourceUrl": "https://motorcomusic.com/event/reggie-watts/",
        "lastScraped": "2025-03-15T13:32:44.144Z",
        "hash": "83ec579cffd32ffc2daf8e6f9a87433d",
        "performers": [
          "Reggie Watts"
        ]
      },
      {
        "id": "4c51db32-2898-4afc-9280-320b64fdc229",
        "name": "Periodic Tables 03 20 2025 with featured speaker Benjamin Chapman",
        "date": "2025-03-20T04:00:00.000Z",
        "type": "music",
        "description": "Event at Motorco Music Hall: Periodic Tables 03 20 2025 with featured speaker Benjamin Chapman. FREE",
        "startTime": "7:00 pm",
        "venueId": "3",
        "sourceUrl": "https://motorcomusic.com/event/periodic-tables-03-20-2025/",
        "lastScraped": "2025-03-15T13:32:44.144Z",
        "hash": "8c64f8b642640e97178aafe62a447866",
        "performers": [
          "Periodic Tables 03 20 2025",
          "featured speaker Benjamin Chapman"
        ]
      },
      {
        "id": "d5d528ab-f95d-460d-8ee3-7351d2e9b6e6",
        "name": "Mentally Im Here",
        "date": "2025-03-21T04:00:00.000Z",
        "type": "music",
        "description": "Event at Motorco Music Hall: Mentally Im Here. Tickets DONATIONS",
        "startTime": "8:00 pm",
        "venueId": "3",
        "sourceUrl": "https://motorcomusic.com/event/mentally-im-here/",
        "lastScraped": "2025-03-15T13:32:44.145Z",
        "hash": "d04225f417e895e7574901af654200e9",
        "performers": [
          "Mentally Im Here"
        ]
      },
      {
        "id": "b78b9425-2e3b-4aca-9e67-60e97cc20f80",
        "name": "Motorco Annual Shrimp Boil with Motorco x Parts & Labor Annual Shrimp Boil",
        "date": "2025-03-22T04:00:00.000Z",
        "type": "music",
        "description": "Event at Motorco Music Hall: Motorco Annual Shrimp Boil with Motorco x Parts & Labor Annual Shrimp Boil. Tickets $20/$25",
        "startTime": "12:00 pm",
        "venueId": "3",
        "sourceUrl": "https://motorcomusic.com/event/motorco-annual-shrimp-boil/",
        "lastScraped": "2025-03-15T13:32:44.145Z",
        "hash": "aca30b6e1d7f10eab5cc1134688baa4d",
        "performers": [
          "Motorco Annual Shrimp Boil",
          "Motorco x Parts",
          "Labor Annual Shrimp Boil"
        ]
      },
      {
        "id": "7c6ba220-e131-417d-bfd6-549b21b6a0c7",
        "name": "Gimme Gimme Disco 3 22 25 with A DISCO DANCE PARTY!",
        "date": "2025-03-22T04:00:00.000Z",
        "type": "music",
        "description": "Event at Motorco Music Hall: Gimme Gimme Disco 3 22 25 with A DISCO DANCE PARTY!. Tickets $20/$23",
        "startTime": "9:00 pm",
        "venueId": "3",
        "sourceUrl": "https://motorcomusic.com/event/gimme-gimme-disco-3-22-25/",
        "lastScraped": "2025-03-15T13:32:44.145Z",
        "hash": "c7f57a6a8fb6bf6376b098c0e1931458",
        "performers": [
          "Gimme Gimme Disco 3 22 25",
          "A DISCO DANCE PARTY!"
        ]
      },
      {
        "id": "55bb5ce4-981e-4f13-9d2d-57050ccad1e1",
        "name": "Will Mcbride Group Matinee Show with RETRO FUSION",
        "date": "2025-03-23T04:00:00.000Z",
        "type": "music",
        "description": "Event at Motorco Music Hall: Will Mcbride Group Matinee Show with RETRO FUSION. Tickets $15/$17",
        "startTime": "1:00 pm",
        "venueId": "3",
        "sourceUrl": "https://motorcomusic.com/event/will-mcbride-group-matinee-show/",
        "lastScraped": "2025-03-15T13:32:44.146Z",
        "hash": "466baf86ca4a43ab027a80abb170c93c",
        "performers": [
          "Will Mcbride Group Matinee Show",
          "RETRO FUSION"
        ]
      },
      {
        "id": "598e5180-9e5d-46e1-8f97-587475b79e86",
        "name": "The Monti Storyslam Fish Out Of Water",
        "date": "2025-03-26T04:00:00.000Z",
        "type": "music",
        "description": "Event at Motorco Music Hall: The Monti Storyslam Fish Out Of Water. Tickets $12",
        "startTime": "7:30 pm",
        "venueId": "3",
        "sourceUrl": "https://motorcomusic.com/event/the-monti-storyslam-fish-out-of-water/",
        "lastScraped": "2025-03-15T13:32:44.146Z",
        "hash": "62fdfc37234d67e2388a5c37b9143fa9",
        "performers": [
          "The Monti Storyslam Fish Out Of Water"
        ]
      },
      {
        "id": "a6881c3a-5810-4c20-ad0f-3e224a4b54d3",
        "name": "Tricky Dick 2025",
        "date": "2025-03-27T04:00:00.000Z",
        "type": "music",
        "description": "Event at Motorco Music Hall: Tricky Dick 2025. Tickets $8/$10",
        "startTime": "8:30 pm",
        "venueId": "3",
        "sourceUrl": "https://motorcomusic.com/event/tricky-dick-2025/",
        "lastScraped": "2025-03-15T13:32:44.146Z",
        "hash": "7044718132fef34e726f38ab19047b46",
        "performers": [
          "Tricky Dick 2025"
        ]
      },
      {
        "id": "27072911-727e-4fa5-ab26-106b72d2e3bc",
        "name": "Maggie Antone with MOLLY FORBES",
        "date": "2025-03-28T04:00:00.000Z",
        "type": "music",
        "description": "Event at Motorco Music Hall: Maggie Antone with MOLLY FORBES. Tickets $20/$25",
        "startTime": "8:00 pm",
        "venueId": "3",
        "sourceUrl": "https://motorcomusic.com/event/maggie-antone/",
        "lastScraped": "2025-03-15T13:32:44.146Z",
        "hash": "cb63f0ca51ebcc8f2de3667ace26f3e3",
        "performers": [
          "Maggie Antone",
          "MOLLY FORBES"
        ]
      },
      {
        "id": "c24aa94e-462b-4a62-9bf7-22cb0f346439",
        "name": "Motorco Rock N Shop 3",
        "date": "2025-03-30T04:00:00.000Z",
        "type": "music",
        "description": "Event at Motorco Music Hall: Motorco Rock N Shop 3. Free",
        "startTime": "12:00 pm",
        "venueId": "3",
        "sourceUrl": "https://motorcomusic.com/event/motorco-rock-n-shop-3/",
        "lastScraped": "2025-03-15T13:32:44.146Z",
        "hash": "e76c55bf692a87241edd98b7cd2b3eae",
        "performers": [
          "Motorco Rock N Shop 3"
        ]
      },
      {
        "id": "d213bb1e-2af3-458f-b997-3155f4c75f7d",
        "name": "A Woman Is A School with author Céline Semaan",
        "date": "2025-04-02T04:00:00.000Z",
        "type": "music",
        "description": "Event at Motorco Music Hall: A Woman Is A School with author Céline Semaan. Tickets $20/$10/$40/$420",
        "startTime": "7:00 pm",
        "venueId": "3",
        "sourceUrl": "https://motorcomusic.com/event/a-woman-is-a-school/",
        "lastScraped": "2025-03-15T13:32:44.146Z",
        "hash": "abcb12782174ad23dd8b44a1a587dcc9",
        "performers": [
          "A Woman Is A School",
          "author Céline Semaan"
        ]
      },
      {
        "id": "3c684d1c-6483-458e-bfe5-cede7ddcaff8",
        "name": "Rebirth Brass Band",
        "date": "2025-04-03T04:00:00.000Z",
        "type": "music",
        "description": "Event at Motorco Music Hall: Rebirth Brass Band. Tickets $35/$40",
        "startTime": "8:00 pm",
        "venueId": "3",
        "sourceUrl": "https://motorcomusic.com/event/rebirth-brass-band/",
        "lastScraped": "2025-03-15T13:32:44.147Z",
        "hash": "dce603f1d12fbdf74c1cc620ee01bb23",
        "performers": [
          "Rebirth Brass Band"
        ]
      },
      {
        "id": "df5b746f-b705-45c1-8449-3bf67c9559e2",
        "name": "Greek with BIKING WITH FRANCIS / THE OPEN",
        "date": "2025-04-04T04:00:00.000Z",
        "type": "music",
        "description": "Event at Motorco Music Hall: Greek with BIKING WITH FRANCIS / THE OPEN. Tickets $20/$25",
        "startTime": "8:00 pm",
        "venueId": "3",
        "sourceUrl": "https://motorcomusic.com/event/greek/",
        "lastScraped": "2025-03-15T13:32:44.147Z",
        "hash": "58e033814b45cb4aebef3b9c9339639e",
        "performers": [
          "Greek",
          "BIKING WITH FRANCIS / THE OPEN"
        ]
      },
      {
        "id": "9f8bb062-fc0b-450c-8c0d-a9c4e1076a1d",
        "name": "Rock Roll Playhouse 4 5 25 with plays THE MUSIC OF TOM PETTY & MORE (FOR KIDS!)",
        "date": "2025-04-05T04:00:00.000Z",
        "type": "music",
        "description": "Event at Motorco Music Hall: Rock Roll Playhouse 4 5 25 with plays THE MUSIC OF TOM PETTY & MORE (FOR KIDS!). Tickets $17/$20",
        "startTime": "12:30 pm",
        "venueId": "3",
        "sourceUrl": "https://motorcomusic.com/event/rock-roll-playhouse-4-5-25/",
        "lastScraped": "2025-03-15T13:32:44.147Z",
        "hash": "8cac65b96b00d1c5614251a203fca9de",
        "performers": [
          "Rock Roll Playhouse 4 5 25",
          "plays THE MUSIC OF TOM PETTY",
          "MORE (FOR KIDS!)"
        ]
      },
      {
        "id": "a68b4c3e-7cf7-4c43-a214-9edafef5fbfb",
        "name": "Debi Tirar Mas Fiestas with THE BAD BUNNY PARTY!",
        "date": "2025-04-05T04:00:00.000Z",
        "type": "music",
        "description": "Event at Motorco Music Hall: Debi Tirar Mas Fiestas with THE BAD BUNNY PARTY!. Tickets $15/$20",
        "startTime": "9:30 pm",
        "venueId": "3",
        "sourceUrl": "https://motorcomusic.com/event/debi-tirar-mas-fiestas/",
        "lastScraped": "2025-03-15T13:32:44.147Z",
        "hash": "60dc8d7291e68cc1bab5b2fb426cb9b2",
        "performers": [
          "Debi Tirar Mas Fiestas",
          "THE BAD BUNNY PARTY!"
        ]
      },
      {
        "id": "f9e32de5-9225-4149-8458-92343e209633",
        "name": "The Weather Station",
        "date": "2025-04-06T04:00:00.000Z",
        "type": "music",
        "description": "Event at Motorco Music Hall: The Weather Station. Tickets $20/$23",
        "startTime": "8:00 pm",
        "venueId": "3",
        "sourceUrl": "https://motorcomusic.com/event/the-weather-station/",
        "lastScraped": "2025-03-15T13:32:44.147Z",
        "hash": "3987e5db053f63f1049b8612f8b40893",
        "performers": [
          "The Weather Station"
        ]
      },
      {
        "id": "4084d24d-3da8-4d32-8060-441251e2f774",
        "name": "The Rocket Summer Hello Good Friend 20th Anniversary Tour with MAE",
        "date": "2025-04-07T04:00:00.000Z",
        "type": "music",
        "description": "Event at Motorco Music Hall: The Rocket Summer Hello Good Friend 20th Anniversary Tour with MAE. Tickets $25/$30",
        "startTime": "8:00 pm",
        "venueId": "3",
        "sourceUrl": "https://motorcomusic.com/event/the-rocket-summer-hello-good-friend-20th-anniversary-tour/",
        "lastScraped": "2025-03-15T13:32:44.148Z",
        "hash": "4792efd2b7d71691f4ce30c7aca77a5e",
        "performers": [
          "The Rocket Summer Hello Good Friend 20th Anniversary Tour",
          "MAE"
        ]
      },
      {
        "id": "c99ef05c-1eb0-4194-a3a4-2c75513779a2",
        "name": "Music Madness 2 with Featuring The Durham Fellows String Quartet",
        "date": "2025-04-10T04:00:00.000Z",
        "type": "music",
        "description": "Event at Motorco Music Hall: Music Madness 2 with Featuring The Durham Fellows String Quartet. Tickets $20",
        "startTime": "7:30 pm",
        "venueId": "3",
        "sourceUrl": "https://motorcomusic.com/event/music-madness-2/",
        "lastScraped": "2025-03-15T13:32:44.148Z",
        "hash": "b1c66790a2d952e91c43eaaa0056cfdd",
        "performers": [
          "Music Madness 2",
          "Featuring The Durham Fellows String Quartet"
        ]
      },
      {
        "id": "4cbe3408-998a-4459-9637-874ffaf090b1",
        "name": "Broadway Rave 4 11 25",
        "date": "2025-04-11T04:00:00.000Z",
        "type": "music",
        "description": "Event at Motorco Music Hall: Broadway Rave 4 11 25. Tickets $20/$23",
        "startTime": "9:00 pm",
        "venueId": "3",
        "sourceUrl": "https://motorcomusic.com/event/broadway-rave-4-11-25/",
        "lastScraped": "2025-03-15T13:32:44.148Z",
        "hash": "a9bb7457d18dc48d10af228451b308ae",
        "performers": [
          "Broadway Rave 4 11 25"
        ]
      },
      {
        "id": "14a26f1a-7461-409b-a8d5-dc8c83866d7e",
        "name": "Daft Disko",
        "date": "2025-04-12T04:00:00.000Z",
        "type": "music",
        "description": "Event at Motorco Music Hall: Daft Disko. Tickets $15/$20",
        "startTime": "9:00 pm",
        "venueId": "3",
        "sourceUrl": "https://motorcomusic.com/event/daft-disko/",
        "lastScraped": "2025-03-15T13:32:44.149Z",
        "hash": "800a96b2c56568a18ae00eaa99741e38",
        "performers": [
          "Daft Disko"
        ]
      },
      {
        "id": "d76d82e1-0469-4695-a984-e60aa2305a7a",
        "name": "2025 Flamenco Vivos Tablao Flamenco Friday Night",
        "date": "2025-04-18T04:00:00.000Z",
        "type": "music",
        "description": "Event at Motorco Music Hall: 2025 Flamenco Vivos Tablao Flamenco Friday Night. Tickets $45/$30/$20 Student",
        "startTime": "8:00 pm",
        "venueId": "3",
        "sourceUrl": "https://motorcomusic.com/event/2025-flamenco-vivos-tablao-flamenco-friday-night/",
        "lastScraped": "2025-03-15T13:32:44.149Z",
        "hash": "9932c226b6b85c7174d9dc94e5dd3acd",
        "performers": [
          "2025 Flamenco Vivos Tablao Flamenco Friday Night"
        ]
      },
      {
        "id": "c81705bd-a848-4dd5-bbf9-22ae2a1b6691",
        "name": "2025 Flamenco Vivos Tablao Flamenco Saturday Matinee",
        "date": "2025-04-19T04:00:00.000Z",
        "type": "music",
        "description": "Event at Motorco Music Hall: 2025 Flamenco Vivos Tablao Flamenco Saturday Matinee. Tickets $45/$30/$20 Student",
        "startTime": "2:00 pm",
        "venueId": "3",
        "sourceUrl": "https://motorcomusic.com/event/2025-flamenco-vivos-tablao-flamenco-saturday-matinee/",
        "lastScraped": "2025-03-15T13:32:44.150Z",
        "hash": "d81995325b1a3cd438e3453e691dbe0c",
        "performers": [
          "2025 Flamenco Vivos Tablao Flamenco Saturday Matinee"
        ]
      },
      {
        "id": "57230982-428e-442c-b245-644a34edca29",
        "name": "2025 Flamenco Vivos Tablao Flamenco Saturday Night",
        "date": "2025-04-19T04:00:00.000Z",
        "type": "music",
        "description": "Event at Motorco Music Hall: 2025 Flamenco Vivos Tablao Flamenco Saturday Night. Tickets $45/$30/$20 Student",
        "startTime": "8:00 pm",
        "venueId": "3",
        "sourceUrl": "https://motorcomusic.com/event/2025-flamenco-vivos-tablao-flamenco-saturday-night/",
        "lastScraped": "2025-03-15T13:32:44.150Z",
        "hash": "cfe7a98fcaa8f4cf286c03002deeb21a",
        "performers": [
          "2025 Flamenco Vivos Tablao Flamenco Saturday Night"
        ]
      },
      {
        "id": "ae94330f-2a2f-42f0-8c39-808bfe288796",
        "name": "Magic Sword with STARBENDERS / MEGA RAN",
        "date": "2025-04-20T04:00:00.000Z",
        "type": "music",
        "description": "Event at Motorco Music Hall: Magic Sword with STARBENDERS / MEGA RAN. Tickets $26/$30",
        "startTime": "8:00 pm",
        "venueId": "3",
        "sourceUrl": "https://motorcomusic.com/event/magic-sword/",
        "lastScraped": "2025-03-15T13:32:44.150Z",
        "hash": "9d7be2dd7a7d9fa4b055874b04652669",
        "performers": [
          "Magic Sword",
          "STARBENDERS / MEGA RAN"
        ]
      },
      {
        "id": "7ff59d86-88a3-445f-aefd-d8292af013b3",
        "name": "Perfect Person",
        "date": "2025-04-24T04:00:00.000Z",
        "type": "music",
        "description": "Event at Motorco Music Hall: Perfect Person. SOLD OUT $32/$37",
        "startTime": "8:00 pm",
        "venueId": "3",
        "sourceUrl": "https://motorcomusic.com/event/perfect-person/",
        "lastScraped": "2025-03-15T13:32:44.150Z",
        "hash": "901cda97de6075b80e8a41671cb1ed19",
        "performers": [
          "Perfect Person"
        ]
      },
      {
        "id": "df54bd20-bc81-438f-b735-cb366cd05cd1",
        "name": "Brother Ali 2 with DJ ABILITIES / JABEE",
        "date": "2025-04-25T04:00:00.000Z",
        "type": "music",
        "description": "Event at Motorco Music Hall: Brother Ali 2 with DJ ABILITIES / JABEE. Tickets $22/$25",
        "startTime": "9:00 pm",
        "venueId": "3",
        "sourceUrl": "https://motorcomusic.com/event/brother-ali-2/",
        "lastScraped": "2025-03-15T13:32:44.150Z",
        "hash": "60abeb21bdec954ad715b9b1b72aecca",
        "performers": [
          "Brother Ali 2"
        ]
      },
      {
        "id": "27e1f4f3-0126-4b6d-9a56-e9402576ec7f",
        "name": "Momma with BRENNAN WEDL",
        "date": "2025-04-26T04:00:00.000Z",
        "type": "music",
        "description": "Event at Motorco Music Hall: Momma with BRENNAN WEDL. Tickets $25/$28",
        "startTime": "8:00 pm",
        "venueId": "3",
        "sourceUrl": "https://motorcomusic.com/event/momma/",
        "lastScraped": "2025-03-15T13:32:44.151Z",
        "hash": "9940aa3be9d96fe17de6cedbe52c563b",
        "performers": [
          "Momma",
          "BRENNAN WEDL"
        ]
      },
      {
        "id": "857e1bf0-b865-4913-bf95-66fa737e09bd",
        "name": "Bartees Strange with EKKO ASTRAL",
        "date": "2025-04-29T04:00:00.000Z",
        "type": "music",
        "description": "Event at Motorco Music Hall: Bartees Strange with EKKO ASTRAL. Tickets $20/$25",
        "startTime": "8:00 pm",
        "venueId": "3",
        "sourceUrl": "https://motorcomusic.com/event/bartees-strange/",
        "lastScraped": "2025-03-15T13:32:44.151Z",
        "hash": "16a853e9911b6458723533cdb8005e29",
        "performers": [
          "Bartees Strange",
          "EKKO ASTRAL"
        ]
      },
      {
        "id": "e22b05da-b2ce-4d48-81e5-031b7c4eff72",
        "name": "Slothrust with WEAKENED FRIENDS",
        "date": "2025-05-01T04:00:00.000Z",
        "type": "music",
        "description": "Event at Motorco Music Hall: Slothrust with WEAKENED FRIENDS. Tickets $20/$25",
        "startTime": "8:00 pm",
        "venueId": "3",
        "sourceUrl": "https://motorcomusic.com/event/slothrust/",
        "lastScraped": "2025-03-15T13:32:44.151Z",
        "hash": "6a6dd28a44f093f281a85074047f048f",
        "performers": [
          "Slothrust",
          "WEAKENED FRIENDS"
        ]
      },
      {
        "id": "9ca93bf9-1e6e-4706-81f5-038c9d26826b",
        "name": "High Vis with MILITARIE GUN / AGE OF APOCALYPSE",
        "date": "2025-05-03T04:00:00.000Z",
        "type": "music",
        "description": "Event at Motorco Music Hall: High Vis with MILITARIE GUN / AGE OF APOCALYPSE. Tickets $25/$28",
        "startTime": "8:00 pm",
        "venueId": "3",
        "sourceUrl": "https://motorcomusic.com/event/high-vis/",
        "lastScraped": "2025-03-15T13:32:44.151Z",
        "hash": "30338da2e8db2507e51344f3c5c01b3f",
        "performers": [
          "High Vis",
          "MILITARIE GUN / AGE OF APOCALYPSE"
        ]
      },
      {
        "id": "8bc446f7-ae03-4f6c-991d-06db1e384c59",
        "name": "Smallpools 05 06 2025",
        "date": "2025-05-06T04:00:00.000Z",
        "type": "music",
        "description": "Event at Motorco Music Hall: Smallpools 05 06 2025. Tickets $27.50/$33",
        "startTime": "8:00 pm",
        "venueId": "3",
        "sourceUrl": "https://motorcomusic.com/event/smallpools-05-06-2025/",
        "lastScraped": "2025-03-15T13:32:44.152Z",
        "hash": "48c71eecfc25fff92f120d3f7171c4de",
        "performers": [
          "Smallpools 05 06 2025"
        ]
      },
      {
        "id": "9861abd2-9904-4b24-875f-05cf87fcc388",
        "name": "Hot In Herre 5 9 25",
        "date": "2025-05-09T04:00:00.000Z",
        "type": "music",
        "description": "Event at Motorco Music Hall: Hot In Herre 5 9 25. Tickets $18/$20",
        "startTime": "9:00 pm",
        "venueId": "3",
        "sourceUrl": "https://motorcomusic.com/event/hot-in-herre-5-9-25/",
        "lastScraped": "2025-03-15T13:32:44.152Z",
        "hash": "4e24bf332f6ba142d0d21df0f6f28dc4",
        "performers": [
          "Hot In Herre 5 9 25"
        ]
      },
      {
        "id": "0e7a0e21-17ce-4061-8bb5-5d2bc261cced",
        "name": "Alien Ant Farm",
        "date": "2025-05-10T04:00:00.000Z",
        "type": "music",
        "description": "Event at Motorco Music Hall: Alien Ant Farm. Tickets $25/$30",
        "startTime": "8:00 pm",
        "venueId": "3",
        "sourceUrl": "https://motorcomusic.com/event/alien-ant-farm/",
        "lastScraped": "2025-03-15T13:32:44.152Z",
        "hash": "ca78acd18e43b7ce9f80419642c8e297",
        "performers": [
          "Alien Ant Farm"
        ]
      },
      {
        "id": "d4580484-6873-464a-a027-5f8a60da7fce",
        "name": "Boston Manor with SPACED / FARMER'S WIFE / ELLIS",
        "date": "2025-05-13T04:00:00.000Z",
        "type": "music",
        "description": "Event at Motorco Music Hall: Boston Manor with SPACED / FARMER'S WIFE / ELLIS. Tickets $25/$30",
        "startTime": "7:00 pm",
        "venueId": "3",
        "sourceUrl": "https://motorcomusic.com/event/boston-manor/",
        "lastScraped": "2025-03-15T13:32:44.152Z",
        "hash": "49fab6ddfc4a488b1c6f4580a5dad72b",
        "performers": [
          "Boston Manor",
          "SPACED / FARMER'S WIFE / ELLIS"
        ]
      },
      {
        "id": "67d64ce0-6b76-4d22-b6cc-54d24545ecfd",
        "name": "Chloe Moriondo 05 16 25 with SEX WEEK",
        "date": "2025-05-16T04:00:00.000Z",
        "type": "music",
        "description": "Event at Motorco Music Hall: Chloe Moriondo 05 16 25 with SEX WEEK. Tickets $22/$26/VIP",
        "startTime": "8:00 pm",
        "venueId": "3",
        "sourceUrl": "https://motorcomusic.com/event/chloe-moriondo-05-16-25/",
        "lastScraped": "2025-03-15T13:32:44.153Z",
        "hash": "2e94f25fd430bc7dc643062037cfb6f9",
        "performers": [
          "Chloe Moriondo 05 16 25",
          "SEX WEEK"
        ]
      },
      {
        "id": "54e23ac3-afd8-4e1b-86fc-b61bfbbcdbba",
        "name": "Brett Dennen River Whyless",
        "date": "2025-05-17T04:00:00.000Z",
        "type": "music",
        "description": "Event at Motorco Music Hall: Brett Dennen River Whyless. Tickets $25/$30",
        "startTime": "8:00 pm",
        "venueId": "3",
        "sourceUrl": "https://motorcomusic.com/event/brett-dennen-river-whyless/",
        "lastScraped": "2025-03-15T13:32:44.153Z",
        "hash": "449b5efde3633507f81cdad19f0fa3db",
        "performers": [
          "Brett Dennen River Whyless"
        ]
      },
      {
        "id": "77904601-ead4-461f-b5a2-49ab29fe3980",
        "name": "The Wedding Present with THE TUBS",
        "date": "2025-05-21T04:00:00.000Z",
        "type": "music",
        "description": "Event at Motorco Music Hall: The Wedding Present with THE TUBS. Tickets $25/$28",
        "startTime": "8:00 pm",
        "venueId": "3",
        "sourceUrl": "https://motorcomusic.com/event/the-wedding-present/",
        "lastScraped": "2025-03-15T13:32:44.153Z",
        "hash": "2e6a6adefadbb0898c3abf60f7c3de34",
        "performers": [
          "The Wedding Present",
          "THE TUBS"
        ]
      },
      {
        "id": "24740d79-18b8-4c4a-8fbe-230b8e02ed53",
        "name": "Annie Dirusso with SQUIRREL FLOWER",
        "date": "2025-05-23T04:00:00.000Z",
        "type": "music",
        "description": "Event at Motorco Music Hall: Annie Dirusso with SQUIRREL FLOWER. Tickets $25.50/$30/$100 VIP",
        "startTime": "8:00 pm",
        "venueId": "3",
        "sourceUrl": "https://motorcomusic.com/event/annie-dirusso/",
        "lastScraped": "2025-03-15T13:32:44.153Z",
        "hash": "6f191ca3bab094743a57ceb51a5de4f0",
        "performers": [
          "Annie Dirusso",
          "SQUIRREL FLOWER"
        ]
      },
      {
        "id": "15ba7fd7-49a7-44dd-8391-1198666ed4af",
        "name": "Nothing Nowhere with SACE6",
        "date": "2025-05-25T04:00:00.000Z",
        "type": "music",
        "description": "Event at Motorco Music Hall: Nothing Nowhere with SACE6. Tickets $25/$28",
        "startTime": "8:00 pm",
        "venueId": "3",
        "sourceUrl": "https://motorcomusic.com/event/nothing-nowhere/",
        "lastScraped": "2025-03-15T13:32:44.154Z",
        "hash": "a2d303b62666a546b7281e3b3ab7ac1d",
        "performers": [
          "Nothing Nowhere",
          "SACE6"
        ]
      },
      {
        "id": "23ff06db-c800-48d1-abcc-c874246bdaf4",
        "name": "Full Of Hell Harms Way with KRUELTY, JARHEAD FERTILIZER, CLIQUE",
        "date": "2025-05-28T04:00:00.000Z",
        "type": "music",
        "description": "Event at Motorco Music Hall: Full Of Hell Harms Way with KRUELTY, JARHEAD FERTILIZER, CLIQUE. Tickets $26/$30",
        "startTime": "6:00 pm",
        "venueId": "3",
        "sourceUrl": "https://motorcomusic.com/event/full-of-hell-harms-way/",
        "lastScraped": "2025-03-15T13:32:44.154Z",
        "hash": "6648116c98e16706546672b4b8bcf1b4",
        "performers": [
          "Full Of Hell Harms Way",
          "KRUELTY",
          "JARHEAD FERTILIZER",
          "CLIQUE"
        ]
      },
      {
        "id": "09e4e7cb-600e-4b16-891b-9ec573958af6",
        "name": "Lights with KING MALA",
        "date": "2025-05-31T04:00:00.000Z",
        "type": "music",
        "description": "Event at Motorco Music Hall: Lights with KING MALA. Tickets $28/$33",
        "startTime": "8:00 pm",
        "venueId": "3",
        "sourceUrl": "https://motorcomusic.com/event/lights/",
        "lastScraped": "2025-03-15T13:32:44.154Z",
        "hash": "f6879a6e88b44a2062875d8f28b1579a",
        "performers": [
          "Lights",
          "KING MALA"
        ]
      },
      {
        "id": "776df00b-f61c-4131-9442-93b6ee2b6db9",
        "name": "Cults 6 11 25 with ZZZAHARA",
        "date": "2025-06-11T04:00:00.000Z",
        "type": "music",
        "description": "Event at Motorco Music Hall: Cults 6 11 25 with ZZZAHARA. Tickets $25/$30",
        "startTime": "8:00 pm",
        "venueId": "3",
        "sourceUrl": "https://motorcomusic.com/event/cults-6-11-25/",
        "lastScraped": "2025-03-15T13:32:44.154Z",
        "hash": "03dbe462af1eed8c94805b90d52ee4da",
        "performers": [
          "Cults 6 11 25",
          "ZZZAHARA"
        ]
      },
      {
        "id": "45764792-5cba-4469-a79e-0eb61a31b2f6",
        "name": "Heart Attack Man with THE DIRTY NIL / CARPOOL / DEAR SEATTLE",
        "date": "2025-06-19T04:00:00.000Z",
        "type": "music",
        "description": "Event at Motorco Music Hall: Heart Attack Man with THE DIRTY NIL / CARPOOL / DEAR SEATTLE. Tickets $27/$30",
        "startTime": "7:00 pm",
        "venueId": "3",
        "sourceUrl": "https://motorcomusic.com/event/heart-attack-man/",
        "lastScraped": "2025-03-15T13:32:44.154Z",
        "hash": "e479741d44a9ab38ab67edcc92756acd",
        "performers": [
          "Heart Attack Man",
          "THE DIRTY NIL / CARPOOL / DEAR SEATTLE"
        ]
      },
      {
        "id": "c6402bf6-9b73-430c-83bd-6e14e4dbc6c0",
        "name": "Julia Wolf with WORRY CLUB / ELLIS",
        "date": "2025-06-22T04:00:00.000Z",
        "type": "music",
        "description": "Event at Motorco Music Hall: Julia Wolf with WORRY CLUB / ELLIS. Tickets $20/$24",
        "startTime": "7:00 pm",
        "venueId": "3",
        "sourceUrl": "https://motorcomusic.com/event/julia-wolf/",
        "lastScraped": "2025-03-15T13:32:44.155Z",
        "hash": "7dd9d6ecb38205a374fc19dae4c1d426",
        "performers": [
          "Julia Wolf",
          "WORRY CLUB / ELLIS"
        ]
      },
      {
        "id": "e7ea068a-e91b-467c-b53a-396fcbee7457",
        "name": "Bailey Spinn with AUTUMN KINGS / THE REQUIEM",
        "date": "2025-06-23T04:00:00.000Z",
        "type": "music",
        "description": "Event at Motorco Music Hall: Bailey Spinn with AUTUMN KINGS / THE REQUIEM. Tickets $23/$27",
        "startTime": "7:00 pm",
        "venueId": "3",
        "sourceUrl": "https://motorcomusic.com/event/bailey-spinn/",
        "lastScraped": "2025-03-15T13:32:44.155Z",
        "hash": "46c408f20c9ad838f644c45baff63cb4",
        "performers": [
          "Bailey Spinn",
          "AUTUMN KINGS / THE REQUIEM"
        ]
      },
      {
        "id": "66d2f9f4-1966-4e13-93ea-10d571ae1b30",
        "name": "Cant Feel My Face",
        "date": "2025-06-27T04:00:00.000Z",
        "type": "music",
        "description": "Event at Motorco Music Hall: Cant Feel My Face. Tickets $18/$20",
        "startTime": "9:00 pm",
        "venueId": "3",
        "sourceUrl": "https://motorcomusic.com/event/cant-feel-my-face/",
        "lastScraped": "2025-03-15T13:32:44.155Z",
        "hash": "fb9abf4e21d5fa69d29ff1040b558e8a",
        "performers": [
          "Cant Feel My Face"
        ]
      },
      {
        "id": "74adf372-6ee7-40a0-9a3a-2282d4460f3e",
        "name": "Rose City Band with POWERS / ROLIN DUO",
        "date": "2025-07-22T04:00:00.000Z",
        "type": "music",
        "description": "Event at Motorco Music Hall: Rose City Band with POWERS / ROLIN DUO. Tickets $20/$22",
        "startTime": "8:00 pm",
        "venueId": "3",
        "sourceUrl": "https://motorcomusic.com/event/rose-city-band/",
        "lastScraped": "2025-03-15T13:32:44.155Z",
        "hash": "beb1741bdff6b9b383cf66b672c020b3",
        "performers": [
          "Rose City Band",
          "POWERS / ROLIN DUO"
        ]
      },
      {
        "id": "b8af39f6-c61e-4506-9dd9-759a2ee9d59e",
        "name": "Cochise 9 12 25",
        "date": "2025-09-12T04:00:00.000Z",
        "type": "music",
        "description": "Event at Motorco Music Hall: Cochise 9 12 25. Tickets $22.50/$25/VIP",
        "startTime": "8:00 pm",
        "venueId": "3",
        "sourceUrl": "https://motorcomusic.com/event/cochise-9-12-25/",
        "lastScraped": "2025-03-15T13:32:44.155Z",
        "hash": "6342f300ee165dce1f9ec05cf2b8df50",
        "performers": [
          "Cochise 9 12 25"
        ]
      }
    ],
    "success": true,
    "scrapedAt": "2025-03-15T13:32:44.156Z"
  },
  {
    "events": [
      {
        "id": "fe86a6fb-22f6-406a-a4b2-3fa4e08b3775",
        "name": "Castle Rat",
        "date": "2025-03-15T00:00:00.000Z",
        "type": "music",
        "description": "Live at Chapel of Bones",
        "startTime": "8:00 PM",
        "venueId": "Chapel of Bones",
        "sourceUrl": "https://www.chapelofbones.com/",
        "lastScraped": "2025-03-15T13:32:47.304Z",
        "hash": "cfcd388da40296b1e4d07e76ed75edd8",
        "performers": [
          "Castle Rat"
        ]
      }
    ],
    "venue": "Chapel of Bones",
    "success": true,
    "scrapedAt": "2025-03-15T13:32:46.156Z"
  }
]